odoo8_addon_connector_woocommerce-8.0.1.0.1-py2.7-nspkg.pth
odoo_addons/connector_woocommerce/__openerp__.py
odoo_addons/connector_woocommerce/backend.py
odoo_addons/connector_woocommerce/related_action.py
odoo_addons/connector_woocommerce/__init__.py
odoo_addons/connector_woocommerce/connector.py
odoo_addons/connector_woocommerce/security/ir.model.access.csv
odoo_addons/connector_woocommerce/model/product.py
odoo_addons/connector_woocommerce/model/backend.py
odoo_addons/connector_woocommerce/model/sale.py
odoo_addons/connector_woocommerce/model/customer.py
odoo_addons/connector_woocommerce/model/__init__.py
odoo_addons/connector_woocommerce/model/product_category.py
odoo_addons/connector_woocommerce/views/backend_view.xml
odoo_addons/connector_woocommerce/unit/mapper.py
odoo_addons/connector_woocommerce/unit/binder.py
odoo_addons/connector_woocommerce/unit/__init__.py
odoo_addons/connector_woocommerce/unit/import_synchronizer.py
odoo_addons/connector_woocommerce/unit/backend_adapter.py
odoo_addons/connector_woocommerce/static/description/icon.png
odoo8_addon_connector_woocommerce-8.0.1.0.1.dist-info/top_level.txt
odoo8_addon_connector_woocommerce-8.0.1.0.1.dist-info/WHEEL
odoo8_addon_connector_woocommerce-8.0.1.0.1.dist-info/RECORD
odoo8_addon_connector_woocommerce-8.0.1.0.1.dist-info/metadata.json
odoo8_addon_connector_woocommerce-8.0.1.0.1.dist-info/DESCRIPTION.rst
odoo8_addon_connector_woocommerce-8.0.1.0.1.dist-info/METADATA
odoo8_addon_connector_woocommerce-8.0.1.0.1.dist-info/namespace_packages.txt
