Metadata-Version: 2.0
Name: odoo8-addon-connector-woocommerce
Version: 8.0.1.0.1
Summary: WooCommerce Connector
Home-page: http://www.openerp.com
Author: UNKNOWN
Author-email: UNKNOWN
License: UNKNOWN
Platform: UNKNOWN
Requires-Dist: odoo (<9.0a,>=8.0a)
Requires-Dist: odoo8-addon-connector
Requires-Dist: odoo8-addon-connector-ecommerce
Requires-Dist: woocommerce
Classifier: Programming Language :: Python :: 2.7
Classifier: Framework :: Odoo
